pyrnc/__init__.py
pyrnc/builder.py
pyrnc/editor.py
pyrnc/filters.py
pyrnc/load.py
pyrnc/parser.py
pyrnc/query.py
pyrnc-0.0.3.dist-info/METADATA
pyrnc-0.0.3.dist-info/WHEEL
pyrnc-0.0.3.dist-info/top_level.txt
pyrnc-0.0.3.dist-info/RECORD
