Metadata-Version: 2.1
Name: pyrnc
Version: 0.0.3
Summary: Third-party tool to work with ruscorpora.ru
Home-page: https://github.com/prodotiscus/pyrnc
Author: Fyodor Sizov
Author-email: f.sizov@yandex.ru
License: UNKNOWN
Project-URL: Bug Tracker, https://github.com/prodotiscus/pyrnc/issues
Platform: UNKNOWN
Classifier: Programming Language :: Python :: 3
Classifier: License :: OSI Approved :: MIT License
Classifier: Operating System :: OS Independent
Requires-Python: >=3.6
Requires-Dist: lxml
Requires-Dist: flask
Requires-Dist: requests
